packer2d/__init__.py
packer2d/packer.py
packer2d/qtree.py
packer2d/rect.py
packer2d/test.py
packer2d-1.0.0b2.dist-info/LICENSE.txt
packer2d-1.0.0b2.dist-info/METADATA
packer2d-1.0.0b2.dist-info/WHEEL
packer2d-1.0.0b2.dist-info/top_level.txt
packer2d-1.0.0b2.dist-info/RECORD
