Metadata-Version: 2.1
Name: packer2d
Version: 1.0.0b2
Summary: 2D bin packer
Home-page: https://gitlab.com/felingineer/packer2d
Download-URL: https://gitlab.com/felingineer/packer2d
Author: Guillermo Romero (Gato)
Author-email: gato@felingineering.com
License: BSD-2-Clause
Keywords: BIN,PACKING,2D
Classifier: Development Status :: 4 - Beta
Classifier: Intended Audience :: Developers
Classifier: Topic :: Utilities
Classifier: License :: OSI Approved :: BSD License
Classifier: Programming Language :: Python :: 3
Classifier: Operating System :: OS Independent
License-File: LICENSE.txt
